header_detail_footer.py
header_detail_footer-2.4.dist-info/DESCRIPTION.rst
header_detail_footer-2.4.dist-info/METADATA
header_detail_footer-2.4.dist-info/RECORD
header_detail_footer-2.4.dist-info/WHEEL
header_detail_footer-2.4.dist-info/metadata.json
header_detail_footer-2.4.dist-info/top_level.txt
