Metadata-Version: 2.0
Name: header-detail-footer
Version: 2.4
Summary: Parse input streams with headers and footers.
Home-page: https://bitbucket.org/ericvsmith/header-detail-footer
Author: Eric V. Smith
Author-email: eric@trueblade.com
License: Apache License Version 2.0
Platform: UNKNOWN
Classifier: Development Status :: 5 - Production/Stable
Classifier: Intended Audience :: Developers
Classifier: License :: OSI Approved :: Apache Software License
Classifier: Topic :: Software Development :: Libraries :: Python Modules
Classifier: Programming Language :: Python :: 2
Classifier: Programming Language :: Python :: 3
